glopan/__init__.py
glopan/__main__.py
glopan/cli.py
glopan/config.py
glopan/glopan.py
glopan-0.0.3.dist-info/entry_points.txt
glopan-0.0.3.dist-info/LICENSE
glopan-0.0.3.dist-info/WHEEL
glopan-0.0.3.dist-info/METADATA
glopan-0.0.3.dist-info/RECORD
