Metadata-Version: 2.1
Name: glopan
Version: 0.0.3
Summary: Glowing Pancake
Home-page: https://github.com/mortenengen/glowing-pancake
Author: Morten Engen
Author-email: mort1eng1@gmail.com
Requires-Python: >=3.7
Classifier: Programming Language :: Python :: 3
Classifier: Operating System :: OS Independent
Requires-Dist: docx2pdf>=0.1.8
Requires-Dist: PyPDF3>=1.0.6
Requires-Dist: rich>=11.2.0
Requires-Dist: typer>=0.4.0
